[
  {
    "name": "Apps",
    "list": [
        {
          "title": "Life Economy",
          "description": "Regulate your life with fake currency. Just wait till I add supply and demand rules to this x.x",
          "link": "https://github.com/binamkayastha/life-economy",
          "linkName": "Github"
        },
        {
          "title": "Goodnight",
          "description": "A google voicekit application to optimize my bedtime ritual and actually get to bed ontime. Ironically I spent multiple days up to 3am writing this.",
          "link": "https://github.com/binamkayastha/goodnight",
          "linkName": "Github"
        },
        {
            "title": "MakeToMove",
            "description": "A giant geodesic dome which was created to encourage people to stop sitting and start moving.",
            "link": "https://github.com/binamkayastha/MakeToMove",
            "linkName": "Github"
        },
        {
            "title": "KeyboardMario",
            "description": "A python program which listens to the event of keypress in archlinux, and plays a note in the mario song for each event.",
            "link": "https://github.com/binamkayastha/KeyboardMario",
            "linkName": "Github"
        },
        {
            "title": "CalendarToImage",
            "description": "My first personal project: a python and autohotkey script which auto opens, screenshots, and crops my google calendar (on windows xp) to perfectly fit my ipod nano. Ah good ol' days",
            "link": "https://github.com/binamkayastha/CalendarToImage",
            "linkName": "Github"
        }
    ]
  },
  {
    "name": "Hack-a-thons",
    "list": [
      {
        "title": "Professor Ciaraldi's Jokes",
        "description": "A compilation of a WPI professor well known for his jokes. If you have any more send them my way ;)",
        "link": "http://binamkayastha.com/ProfCiaraldiJokes/",
        "linkName": "Website!"
      },
      {
        "title": "OneArmBand (1st)",
        "description": "A project where we had various devices linked together through a server in order to make music and notes from one arm",
        "link": "https://github.com/OnlineHackathon/OneArmBand",
        "linkName": "Github"
      },
      {
        "title": "HoloSense (Best use of Spacial Sound)",
        "description": "Made echolocation app which allows you to walk around indoors without a cane with a hololens."
      },
      {
        "title": "Dr. AllerG (2nd and most liked)",
        "description": "A google assistant app that tells you whether or not you can eat a certain food"
      },
      {
        "title": "alphaStep",
        "description": "A webapp which can teach you to write any Unicode letter or letters, meaning any font and any lanaguage.",
        "link": "https://github.com/binamkayastha/alphaWorm",
        "linkName": "Github"
      }
    ]
  }
]
